zum/__init__.py
zum/cli/__init__.py
zum/cli/core.py
zum/cli/generators.py
zum/cli/utils.py
zum/configs/__init__.py
zum/configs/core.py
zum/configs/errors.py
zum/constants.py
zum/engine.py
zum/executor.py
zum/requests/__init__.py
zum/requests/core.py
zum/requests/errors.py
zum/requests/helpers.py
zum/requests/models.py
zum/requests/validations.py
zum/utils.py
zum-0.3.0.dist-info/entry_points.txt
zum-0.3.0.dist-info/LICENSE
zum-0.3.0.dist-info/WHEEL
zum-0.3.0.dist-info/METADATA
zum-0.3.0.dist-info/RECORD
